Wellness_Bot-0.1.1.data/scripts/start
Wellness_Bot-0.1.1.dist-info/METADATA
Wellness_Bot-0.1.1.dist-info/RECORD
Wellness_Bot-0.1.1.dist-info/WHEEL
Wellness_Bot-0.1.1.dist-info/top_level.txt
app/.DS_Store
app/__init__.py
app/__main__.py
app/__version__.py
app/challenge.py
app/challenge_runner.py
app/challenges/10crunches.yaml
app/challenges/10ice-climbers.yaml
app/challenges/5burpees.yaml
app/challenges/5pushups.yaml
app/challenges/5squats.yaml
app/challenges/backstretch.yaml
app/challenges/challenge_template.yaml
app/challenges/mScale3 copy.yaml
app/challenges/mScale3.yaml
